motionSegmentation/BsplineFourier.py
motionSegmentation/__init__.py
motionSegmentation/bfSolver.py
motionSegmentation/motionCorrect.py
motionSegmentation/segment.py
motionSegmentation-2.9.2.dist-info/LICENSE
motionSegmentation-2.9.2.dist-info/METADATA
motionSegmentation-2.9.2.dist-info/WHEEL
motionSegmentation-2.9.2.dist-info/top_level.txt
motionSegmentation-2.9.2.dist-info/RECORD
