Metadata-Version: 2.1
Name: motionSegmentation
Version: 2.9.2
Summary: Explicit spatio-temporal regularization of motion tracking.
Author-email: Wei Xuan Chan <w.x.chan1986@gmail.com>
License: MIT License
Project-URL: Homepage, https://github.com/WeiXuanChan/motionSegmentation
Keywords: explicit,motion,regularization
Classifier: License :: OSI Approved :: MIT License
Classifier: Programming Language :: Python
Classifier: Programming Language :: Python :: 3
Requires-Python: >=3.6
License-File: LICENSE
Requires-Dist: numpy
Requires-Dist: autoD
Requires-Dist: scipy
Requires-Dist: trimesh
Requires-Dist: medImgProc
Requires-Dist: nfft
Provides-Extra: dev
Requires-Dist: modulus ; extra == 'dev'
